threepwood/__init__.py
threepwood/cli.py
threepwood/placeholder.py
threepwood/py.typed
threepwood/version.py
threepwood-0.0.2.dist-info/LICENSE
threepwood-0.0.2.dist-info/METADATA
threepwood-0.0.2.dist-info/WHEEL
threepwood-0.0.2.dist-info/entry_points.txt
threepwood-0.0.2.dist-info/top_level.txt
threepwood-0.0.2.dist-info/RECORD
